{"chunkX":-36,"chunkY":-30,"biomeId":"meadow","tiles":[0,0,4,0,0,0,0,0,3,0,10,0,4,0,0,0,3,0,10,0,0,10,0,0,2,0,0,0,0,0,0,0,0,0,4,0,0,0,4,2,0,3,0,0,0,4,0,0,0,0,0,0,0,0,0,4,4,0,2,0,0,0,0,0,0,4,0,0,0,0,0,0,0,4,10,0,0,4,2,4,0,0,4,0,0,0,0,0,0,0,10,0,0,0,0,0,2,0,0,4,0,0,0,0,0,0,0,0,4,0,0,0,0,0,4,0,0,0,0,4,0,0,0,0,0,4,0,0,0,0,0,0,0,0,0,0,0,0,3,0,0,0,0,0,2,0,0,0,0,0,4,0,0,0,0,0,0,0,10,0,0,0,4,0,0,0,2,2,0,0,0,0,0,0,0,0,0,0,0,0,0,3,0,0,2,0,0,0,0,2,0,0,0,0,0,0,2,0,4,2,0,0,2,0,0,0,4,0,0,0,0,0,0,0,0,0,0,4,4,0,0,4,10,10,0,0,0,3,0,0,3,0,4,2,0,0,0,0,0,4,2,0,4,4,0,0,0,0,0,0,0,4,0,0,0,0],"solids":[false,false,false,false,false,false,false,false,false,false,false,false,false,false,false,false,false,false,false,false,false,false,false,false,false,false,false,false,false,false,false,false,false,false,false,false,false,false,false,false,false,false,false,false,false,false,false,false,false,false,false,false,false,false,false,false,false,false,false,false,false,false,false,false,false,false,false,false,false,false,false,false,false,false,false,false,false,false,false,false,false,false,false,false,false,false,false,false,false,false,false,false,false,false,false,false,false,false,false,false,false,false,false,false,false,false,false,false,false,false,false,false,false,false,false,false,false,false,false,false,false,false,false,false,false,false,false,false,false,false,false,false,false,false,false,false,false,false,false,false,false,false,false,false,false,false,false,false,false,false,false,false,false,false,false,false,false,false,false,false,false,false,false,false,false,false,false,false,false,false,false,false,false,false,false,false,false,false,false,false,false,false,false,false,false,false,false,false,false,false,false,false,false,false,false,false,false,false,false,false,false,false,false,false,false,false,false,false,false,false,false,false,false,false,false,false,false,false,false,false,false,false,false,false,false,false,false,false,false,false,false,false,false,false,false,false,false,false,false,false,false,false,false,false,false,false,false,false,false,false,false,false,false,false,false,false],"resources":[{"id":"stick_pile","x":-18288,"y":-15344,"health":1,"maxHealth":1,"tool":"none","toolTier":0,"drops":[{"item":"stick","min":1,"max":3}],"respawnTime":60,"color":"#6B4226","size":10,"depleted":false,"depletedAt":0},{"id":"stick_pile","x":-18416,"y":-15280,"health":1,"maxHealth":1,"tool":"none","toolTier":0,"drops":[{"item":"stick","min":1,"max":3}],"respawnTime":60,"color":"#6B4226","size":10,"depleted":false,"depletedAt":0},{"id":"stick_pile","x":-17968,"y":-15280,"health":1,"maxHealth":1,"tool":"none","toolTier":0,"drops":[{"item":"stick","min":1,"max":3}],"respawnTime":60,"color":"#6B4226","size":10,"depleted":false,"depletedAt":0},{"id":"stick_pile","x":-18096,"y":-15216,"health":1,"maxHealth":1,"tool":"none","toolTier":0,"drops":[{"item":"stick","min":1,"max":3}],"respawnTime":60,"color":"#6B4226","size":10,"depleted":false,"depletedAt":0},{"id":"stick_pile","x":-18416,"y":-15152,"health":1,"maxHealth":1,"tool":"none","toolTier":0,"drops":[{"item":"stick","min":1,"max":3}],"respawnTime":60,"color":"#6B4226","size":10,"depleted":false,"depletedAt":0},{"id":"stick_pile","x":-18224,"y":-15152,"health":1,"maxHealth":1,"tool":"none","toolTier":0,"drops":[{"item":"stick","min":1,"max":3}],"respawnTime":60,"color":"#6B4226","size":10,"depleted":false,"depletedAt":0},{"id":"stick_pile","x":-17968,"y":-15152,"health":1,"maxHealth":1,"tool":"none","toolTier":0,"drops":[{"item":"stick","min":1,"max":3}],"respawnTime":60,"color":"#6B4226","size":10,"depleted":false,"depletedAt":0},{"id":"stick_pile","x":-17968,"y":-15088,"health":1,"maxHealth":1,"tool":"none","toolTier":0,"drops":[{"item":"stick","min":1,"max":3}],"respawnTime":60,"color":"#6B4226","size":10,"depleted":false,"depletedAt":0},{"id":"stick_pile","x":-18288,"y":-15024,"health":1,"maxHealth":1,"tool":"none","toolTier":0,"drops":[{"item":"stick","min":1,"max":3}],"respawnTime":60,"color":"#6B4226","size":10,"depleted":false,"depletedAt":0},{"id":"stick_pile","x":-18224,"y":-15024,"health":1,"maxHealth":1,"tool":"none","toolTier":0,"drops":[{"item":"stick","min":1,"max":3}],"respawnTime":60,"color":"#6B4226","size":10,"depleted":false,"depletedAt":0},{"id":"stick_pile","x":-18352,"y":-14960,"health":1,"maxHealth":1,"tool":"none","toolTier":0,"drops":[{"item":"stick","min":1,"max":3}],"respawnTime":60,"color":"#6B4226","size":10,"depleted":false,"depletedAt":0},{"id":"stick_pile","x":-18224,"y":-14896,"health":1,"maxHealth":1,"tool":"none","toolTier":0,"drops":[{"item":"stick","min":1,"max":3}],"respawnTime":60,"color":"#6B4226","size":10,"depleted":false,"depletedAt":0},{"id":"stick_pile","x":-18096,"y":-14896,"health":1,"maxHealth":1,"tool":"none","toolTier":0,"drops":[{"item":"stick","min":1,"max":3}],"respawnTime":60,"color":"#6B4226","size":10,"depleted":false,"depletedAt":0},{"id":"stick_pile","x":-17968,"y":-14896,"health":1,"maxHealth":1,"tool":"none","toolTier":0,"drops":[{"item":"stick","min":1,"max":3}],"respawnTime":60,"color":"#6B4226","size":10,"depleted":false,"depletedAt":0},{"id":"loose_stone","x":-18224,"y":-15344,"health":1,"maxHealth":1,"tool":"none","toolTier":0,"drops":[{"item":"stone","min":1,"max":2}],"respawnTime":90,"color":"#999999","size":10,"depleted":false,"depletedAt":0},{"id":"loose_stone","x":-17968,"y":-15216,"health":1,"maxHealth":1,"tool":"none","toolTier":0,"drops":[{"item":"stone","min":1,"max":2}],"respawnTime":90,"color":"#999999","size":10,"depleted":false,"depletedAt":0},{"id":"loose_stone","x":-18416,"y":-15152,"health":1,"maxHealth":1,"tool":"none","toolTier":0,"drops":[{"item":"stone","min":1,"max":2}],"respawnTime":90,"color":"#999999","size":10,"depleted":false,"depletedAt":0},{"id":"loose_stone","x":-18416,"y":-15024,"health":1,"maxHealth":1,"tool":"none","toolTier":0,"drops":[{"item":"stone","min":1,"max":2}],"respawnTime":90,"color":"#999999","size":10,"depleted":false,"depletedAt":0},{"id":"loose_stone","x":-18160,"y":-15024,"health":1,"maxHealth":1,"tool":"none","toolTier":0,"drops":[{"item":"stone","min":1,"max":2}],"respawnTime":90,"color":"#999999","size":10,"depleted":false,"depletedAt":0},{"id":"loose_stone","x":-18032,"y":-14960,"health":1,"maxHealth":1,"tool":"none","toolTier":0,"drops":[{"item":"stone","min":1,"max":2}],"respawnTime":90,"color":"#999999","size":10,"depleted":false,"depletedAt":0},{"id":"loose_stone","x":-18416,"y":-14896,"health":1,"maxHealth":1,"tool":"none","toolTier":0,"drops":[{"item":"stone","min":1,"max":2}],"respawnTime":90,"color":"#999999","size":10,"depleted":false,"depletedAt":0},{"id":"wood_oak","x":-18160,"y":-15280,"health":30,"maxHealth":30,"tool":"axe","toolTier":0,"drops":[{"item":"wood","min":2,"max":4}],"respawnTime":300,"color":"#5a3d1a","size":32,"depleted":false,"depletedAt":0},{"id":"wood_oak","x":-18224,"y":-15216,"health":30,"maxHealth":30,"tool":"axe","toolTier":0,"drops":[{"item":"wood","min":2,"max":4}],"respawnTime":300,"color":"#5a3d1a","size":32,"depleted":false,"depletedAt":0},{"id":"wood_oak","x":-18416,"y":-15152,"health":30,"maxHealth":30,"tool":"axe","toolTier":0,"drops":[{"item":"wood","min":2,"max":4}],"respawnTime":300,"color":"#5a3d1a","size":32,"depleted":false,"depletedAt":0},{"id":"wood_oak","x":-18032,"y":-15152,"health":30,"maxHealth":30,"tool":"axe","toolTier":0,"drops":[{"item":"wood","min":2,"max":4}],"respawnTime":300,"color":"#5a3d1a","size":32,"depleted":false,"depletedAt":0},{"id":"wood_oak","x":-18288,"y":-15088,"health":30,"maxHealth":30,"tool":"axe","toolTier":0,"drops":[{"item":"wood","min":2,"max":4}],"respawnTime":300,"color":"#5a3d1a","size":32,"depleted":false,"depletedAt":0},{"id":"wood_oak","x":-18352,"y":-15024,"health":30,"maxHealth":30,"tool":"axe","toolTier":0,"drops":[{"item":"wood","min":2,"max":4}],"respawnTime":300,"color":"#5a3d1a","size":32,"depleted":false,"depletedAt":0},{"id":"wood_oak","x":-18288,"y":-15024,"health":30,"maxHealth":30,"tool":"axe","toolTier":0,"drops":[{"item":"wood","min":2,"max":4}],"respawnTime":300,"color":"#5a3d1a","size":32,"depleted":false,"depletedAt":0},{"id":"wood_oak","x":-18416,"y":-14896,"health":30,"maxHealth":30,"tool":"axe","toolTier":0,"drops":[{"item":"wood","min":2,"max":4}],"respawnTime":300,"color":"#5a3d1a","size":32,"depleted":false,"depletedAt":0},{"id":"stone_node","x":-18288,"y":-15344,"health":40,"maxHealth":40,"tool":"pickaxe","toolTier":0,"drops":[{"item":"stone","min":1,"max":3}],"respawnTime":300,"color":"#888888","size":24,"depleted":false,"depletedAt":0},{"id":"stone_node","x":-18416,"y":-15152,"health":40,"maxHealth":40,"tool":"pickaxe","toolTier":0,"drops":[{"item":"stone","min":1,"max":3}],"respawnTime":300,"color":"#888888","size":24,"depleted":false,"depletedAt":0},{"id":"stone_node","x":-18224,"y":-15152,"health":40,"maxHealth":40,"tool":"pickaxe","toolTier":0,"drops":[{"item":"stone","min":1,"max":3}],"respawnTime":300,"color":"#888888","size":24,"depleted":false,"depletedAt":0},{"id":"stone_node","x":-17968,"y":-15088,"health":40,"maxHealth":40,"tool":"pickaxe","toolTier":0,"drops":[{"item":"stone","min":1,"max":3}],"respawnTime":300,"color":"#888888","size":24,"depleted":false,"depletedAt":0},{"id":"stone_node","x":-18352,"y":-14960,"health":40,"maxHealth":40,"tool":"pickaxe","toolTier":0,"drops":[{"item":"stone","min":1,"max":3}],"respawnTime":300,"color":"#888888","size":24,"depleted":false,"depletedAt":0},{"id":"stone_node","x":-18224,"y":-14896,"health":40,"maxHealth":40,"tool":"pickaxe","toolTier":0,"drops":[{"item":"stone","min":1,"max":3}],"respawnTime":300,"color":"#888888","size":24,"depleted":false,"depletedAt":0},{"id":"stone_node","x":-17968,"y":-14896,"health":40,"maxHealth":40,"tool":"pickaxe","toolTier":0,"drops":[{"item":"stone","min":1,"max":3}],"respawnTime":300,"color":"#888888","size":24,"depleted":false,"depletedAt":0},{"id":"berry_bush","x":-18352,"y":-15344,"health":1,"maxHealth":1,"tool":"none","toolTier":0,"drops":[{"item":"berries","min":1,"max":3}],"respawnTime":180,"color":"#c0392b","size":16,"depleted":false,"depletedAt":0},{"id":"berry_bush","x":-18096,"y":-15216,"health":1,"maxHealth":1,"tool":"none","toolTier":0,"drops":[{"item":"berries","min":1,"max":3}],"respawnTime":180,"color":"#c0392b","size":16,"depleted":false,"depletedAt":0},{"id":"berry_bush","x":-18416,"y":-15088,"health":1,"maxHealth":1,"tool":"none","toolTier":0,"drops":[{"item":"berries","min":1,"max":3}],"respawnTime":180,"color":"#c0392b","size":16,"depleted":false,"depletedAt":0},{"id":"berry_bush","x":-18032,"y":-15088,"health":1,"maxHealth":1,"tool":"none","toolTier":0,"drops":[{"item":"berries","min":1,"max":3}],"respawnTime":180,"color":"#c0392b","size":16,"depleted":false,"depletedAt":0},{"id":"berry_bush","x":-18096,"y":-15024,"health":1,"maxHealth":1,"tool":"none","toolTier":0,"drops":[{"item":"berries","min":1,"max":3}],"respawnTime":180,"color":"#c0392b","size":16,"depleted":false,"depletedAt":0},{"id":"berry_bush","x":-18224,"y":-14960,"health":1,"maxHealth":1,"tool":"none","toolTier":0,"drops":[{"item":"berries","min":1,"max":3}],"respawnTime":180,"color":"#c0392b","size":16,"depleted":false,"depletedAt":0},{"id":"berry_bush","x":-17968,"y":-14960,"health":1,"maxHealth":1,"tool":"none","toolTier":0,"drops":[{"item":"berries","min":1,"max":3}],"respawnTime":180,"color":"#c0392b","size":16,"depleted":false,"depletedAt":0},{"id":"berry_bush","x":-18416,"y":-14896,"health":1,"maxHealth":1,"tool":"none","toolTier":0,"drops":[{"item":"berries","min":1,"max":3}],"respawnTime":180,"color":"#c0392b","size":16,"depleted":false,"depletedAt":0}],"spawnPoints":[{"enemyId":"greyling","x":-18000,"y":-15184,"config":{"id":"greyling","name":"Greyling","health":20,"damage":5,"speed":60,"xpReward":5,"drops":[{"item":"greyling_hide","chance":0.5,"min":1,"max":1}],"minGradient":0,"maxGradient":1,"densityAtLeft":0.03,"densityAtRight":0.06,"color":"#7f8c8d","size":20,"behavior":"wander","aggroRange":128,"deaggroRange":256}}]}